era5epw/__init__.py
era5epw/ads.py
era5epw/cds.py
era5epw/logcfg.py
era5epw/main.py
era5epw/utils.py
era5epw-0.2.0.dist-info/LICENSE
era5epw-0.2.0.dist-info/METADATA
era5epw-0.2.0.dist-info/WHEEL
era5epw-0.2.0.dist-info/entry_points.txt
era5epw-0.2.0.dist-info/RECORD
