Metadata-Version: 2.1
Name: era5epw
Version: 0.2.0
Summary: A tool to convert ERA5/ECMWF data to EnergyPlus Weather (EPW) format
Author: Antoine Galataud
Author-email: antoine@foobot.io
Requires-Python: >=3.12,<3.13
Classifier: Programming Language :: Python :: 3
Classifier: Programming Language :: Python :: 3.12
Requires-Dist: cdsapi (==0.7.6)
Requires-Dist: netcdf4 (==1.7.2)
Requires-Dist: numpy (==1.26.4)
Requires-Dist: pandas (==2.2.3)
Requires-Dist: xarray (==2025.7.0)
